{
  "slug": "one-person-company-startup-guide-2026",
  "title": "2026年一人公司创业完全指南：从0到1的独立创业方法论",
  "summary": "一文讲透一人公司的核心理念、启动步骤、法律合规与风险控制，帮助你用最少的资源启动最有价值的个人事业。",
  "content": "## 什么是一人公司\n\n一人公司（Solopreneur）不是一个人的小生意，而是一种全新的工作与生活方式。它意味着你作为独立个体，利用技术工具、平台经济和全球化资源，打造可持续盈利的个人事业。\n\n## 启动一人公司的5个关键步骤\n\n### 1. 找到你的利基市场\n- 分析你的技能组合与市场需求的重叠区域\n- 选择足够小但足够值钱的细分市场\n- 案例：从PPT设计师到年入百万的演示咨询顾问\n\n### 2. 构建最小可行产品（MVP）\n- 不追求完美，先验证需求\n- 用Notion/Airtable/Glide等无代码工具快速搭建\n- 72小时内完成第一个版本的发布\n\n### 3. 建立获客渠道\n- 内容营销：公众号、知乎、小红书持续输出\n- SEO优化：围绕长尾关键词建立搜索流量\n- 社交证明：案例展示、客户评价、行业背书\n\n### 4. 自动化运营\n- 用Zapier/Make自动化重复工作\n- AI客服处理80%的常见问题\n- 模板化交付流程，降低边际成本\n\n### 5. 持续迭代与规模化\n- 数据驱动的决策机制\n- 产品化服务：从卖时间到卖产品\n- 建立复购与推荐机制\n\n## 一人公司常见的3个误区\n\n1. **误区一：必须全栈**——你只需要精通1-2项核心技能，其余外包或用工具解决\n2. **误区二：前期需要大投入**——一人公司的启动成本可以低至几百元\n3. **误区三：孤军奋战**——你可以加入社区、找合伙人项目、雇佣虚拟助理",
  "category": "创业指南",
  "tags": ["一人公司", "独立创业", "创业方法论", "Solopreneur", "MVP"],
  "author": "songhy",
  "publishedAt": "2026-06-20",
  "coverImage": "/images/og-default.png",
  "sourceName": "一人公司",
  "sourceUrl": "/guide",
  "featured": true,
  "readTime": 8
}
